{
  "project_info": {
    "project_number": "187460176489",
    "project_id": "chatapp1-c5309",
    "storage_bucket": "chatapp1-c5309.appspot.com"
  },
  "client": [
    {
      "client_info": {
        "mobilesdk_app_id": "1:187460176489:android:7b592041d31ff23356b0f8",
        "android_client_info": {
          "package_name": "com.example.chatapp"
        }
      },
      "oauth_client": [],
      "api_key": [
        {
          "current_key": "AIzaSyCrzkZBP1tlFzn2OqZDNmVnQ4sSbfDjjJc"
        }
      ],
      "services": {
        "appinvite_service": {
          "other_platform_oauth_client": []
        }
      }
    }
  ],
  "configuration_version": "1"
}